atat/README.md
atat/__init__.py
atat/atat.py
atat/__pycache__/__init__.cpython-311.pyc
atat/config/README.md
atat/config/config.json
atat/config/img/free_benchmark.png
atat/core/common_config.py
atat/core/__pycache__/file_check_util.cpython-311.pyc
atat/core/__pycache__/log.cpython-311.pyc
atat/core/__pycache__/utils.cpython-311.pyc
atat/core/common/const.py
atat/core/common/exceptions.py
atat/core/common/file_check.py
atat/core/common/log.py
atat/core/common/utils.py
atat/core/data_dump/data_collector.py
atat/core/data_dump/json_writer.py
atat/core/data_dump/scope.py
atat/core/data_dump/data_processor/base.py
atat/core/data_dump/data_processor/factory.py
atat/core/data_dump/data_processor/pytorch_processor.py
atat/mindspore/__init__.py
atat/mindspore/ms_config.py
atat/mindspore/task_handler_factory.py
atat/mindspore/debugger/__init__.py
atat/mindspore/debugger/debugger_config.py
atat/mindspore/debugger/precision_debugger.py
atat/mindspore/doc/dump.md
atat/mindspore/dump/__init__.py
atat/mindspore/dump/api_kbk_dump.py
atat/mindspore/dump/dump_tool_factory.py
atat/mindspore/dump/kernel_graph_dump.py
atat/mindspore/overflow_check/__init__.py
atat/mindspore/overflow_check/kernel_graph_overflow_check.py
atat/mindspore/overflow_check/overflow_check_tool_factory.py
atat/msprobe_test.egg-info/PKG-INFO
atat/msprobe_test.egg-info/SOURCES.txt
atat/msprobe_test.egg-info/dependency_links.txt
atat/msprobe_test.egg-info/not-zip-safe
atat/msprobe_test.egg-info/requires.txt
atat/msprobe_test.egg-info/top_level.txt
atat/pytorch/__init__.py
atat/pytorch/module_processer.py
atat/pytorch/parse.py
atat/pytorch/pt_config.py
atat/pytorch/service.py
atat/pytorch/__pycache__/__init__.cpython-311.pyc
atat/pytorch/__pycache__/module_processer.cpython-311.pyc
atat/pytorch/__pycache__/service.cpython-311.pyc
atat/pytorch/advisor/advisor.py
atat/pytorch/advisor/advisor_const.py
atat/pytorch/advisor/advisor_result.py
atat/pytorch/api_accuracy_checker/.keep
atat/pytorch/api_accuracy_checker/__init__.py
atat/pytorch/api_accuracy_checker/config.yaml
atat/pytorch/api_accuracy_checker/common/.keep
atat/pytorch/api_accuracy_checker/common/__init__.py
atat/pytorch/api_accuracy_checker/common/config.py
msprobe_test-1.0.4.dist-info/LICENSE
msprobe_test-1.0.4.dist-info/METADATA
msprobe_test-1.0.4.dist-info/WHEEL
msprobe_test-1.0.4.dist-info/entry_points.txt
msprobe_test-1.0.4.dist-info/top_level.txt
msprobe_test-1.0.4.dist-info/RECORD
